setuptools_parcels/__init__.py
setuptools_parcels-0.0.8.dist-info/DESCRIPTION.rst
setuptools_parcels-0.0.8.dist-info/METADATA
setuptools_parcels-0.0.8.dist-info/RECORD
setuptools_parcels-0.0.8.dist-info/WHEEL
setuptools_parcels-0.0.8.dist-info/entry_points.txt
setuptools_parcels-0.0.8.dist-info/metadata.json
setuptools_parcels-0.0.8.dist-info/top_level.txt
